andromeda_chain/__init__.py
andromeda_chain/andromeda_chain.py
andromeda_chain/prompt.py
andromeda_chain/response.py
andromeda_chain/version.py
andromeda_chain-0.2.dist-info/LICENSE
andromeda_chain-0.2.dist-info/METADATA
andromeda_chain-0.2.dist-info/WHEEL
andromeda_chain-0.2.dist-info/top_level.txt
andromeda_chain-0.2.dist-info/RECORD
